flask_jwt_next/__init__.py
flask_jwt_next/__version__.py
flask_jwt_next-1.0.2.dist-info/LICENSE
flask_jwt_next-1.0.2.dist-info/METADATA
flask_jwt_next-1.0.2.dist-info/WHEEL
flask_jwt_next-1.0.2.dist-info/top_level.txt
flask_jwt_next-1.0.2.dist-info/RECORD
