Metadata-Version: 2.1
Name: flask-jwt-next
Version: 1.0.2
Summary: JWT token authentication for Flask apps.
Home-page: https://github.com/yannickkirschen/flask-jwt-next
Author: Yannick Kirschen
Author-email: github.yannickkirschen@protonmail.com
License: MIT
Platform: UNKNOWN
Classifier: Programming Language :: Python :: 3
Classifier: License :: OSI Approved :: GNU General Public License v3 (GPLv3)
Classifier: Operating System :: OS Independent
Classifier: Operating System :: OS Independent
Classifier: Intended Audience :: Developers
Classifier: Natural Language :: English
